<!DOCTYPE frameset SYSTEM "frameset.dtd">
<frameset>
<predicate lemma="growl">
<note>
  Frames file for 'growl' based on survey of sentences in the WSJ
  corpus.
</note>

<roleset id="growl.01" name="to speak in an angry or surly manner" vncls="37.3 40.2">
<roles>
  <role descr="growler" n="0">
        <vnrole vncls="40.2" vntheta="Agent"/>
        <vnrole vncls="37.3" vntheta="Agent"/></role>
  <role descr="utterance" n="1">
        <vnrole vncls="40.2" vntheta="Theme"/>
        <vnrole vncls="37.3" vntheta="Topic"/></role>
</roles>

<example name="transitive">
<inflection aspect="ns" form="full" person="third" tense="present" voice="active"/>
<text>
 `` Babies , kiddies , '' growls [*T*-1] their manager -- a fellow named [*-2] Earl Weaver , who , in a different time , [*T*-3] handled four World Series teams and now [*T*-3] handles the Gold Coast Suns .
</text>
	<rel>growls</rel>
	<arg n="1">[*T*-1] -&gt;  Babies , kiddies ,</arg>
	<arg n="0">their manager -- a fellow named [*-2] Earl Weaver , who , in a different time , [*T*-3] handled four World Series teams and now [*T*-3] handles the Gold Coast Suns</arg>
</example>


</roleset>
</predicate>


</frameset>
