<!DOCTYPE frameset SYSTEM "frameset.dtd">
<frameset>
<predicate lemma="cripple">
<note>
  Frames file for 'cripple' based on sentences in wsj.  No Verbnet
  entry at the moment.
</note>

<roleset id="cripple.01" name="injure very badly, disable" vncls="-">
<roles>
  <role descr="causer, agent" n="0"/>
  <role descr="victim" n="1"/>
  <role descr="instrument" n="2"/>
</roles>

<example name="passive, no agent">
<inflection aspect="ns" form="participle" person="ns" tense="present" voice="passive"/>
<text>
    But a Soviet bank here would be crippled *trace* unless Moscow
    found a way  to settle the $188 million debt, which  was lent to
    the country's short-lived democratic Kerensky government before
    the Communists seized power in 1917. 
</text>
        <arg f="MOD" n="M">would</arg>
        <rel>crippled</rel>
        <arg n="1">*trace* -&gt;  a Soviet bank here</arg>
        <arg f="ADV" n="M">unless Moscow found a way to settle the
        $188 million debt, which  was lent to the country's
        short-lived democratic Kerensky government before the
        Communists seized power in 1917 </arg> 
</example>

<example name="passive with agent">
<inflection aspect="ns" form="participle" person="ns" tense="present" voice="passive"/>
<text>
     Founded as the Examiner in 1903 by Mr. Hearst, the Herald was
     crippled *trace* by a bitter, decade-long strike that began in
     1967 and cut circulation in half. 
</text>
        <arg n="M">Founded as the Examiner in 1903 by Mr. Hearst</arg>
        <rel>crippled</rel>
        <arg n="1">*trace* -&gt;  the Herald</arg>
        <arg f="by" n="0">[ a bitter , decade-long strike] [ that
        began in 1967 and cut circulation in half]</arg> 
</example>

<example name="active">
<inflection aspect="perfect" form="participle" person="third" tense="present" voice="active"/>
<text>
    An 11-week dispute involving Australia's 1,640 domestic pilots has
    slashed airline earnings and crippled much of the continent's
    tourist industry. 
</text>
        <arg n="0">An 11-week dispute involving Australia's 1,640
        domestic pilots</arg> 
        <rel>crippled</rel>
        <arg n="1">much of the continent 's tourist industry</arg>
</example>

<example name="with instrument">
  <inflection aspect="ns" form="full" person="ns" tense="past" voice="active"/>
  <text>
    Mary crippled John's fragile self-esteem with her relentless
    scornful insults.
  </text>
  <arg n="0">Mary</arg>
  <rel>crippled</rel>
  <arg n="1">John's fragile self-esteem</arg>
  <arg f="with" n="2">her relentless scornful insults</arg>
</example>

<note>
</note>

</roleset>
</predicate>
</frameset>
