<!DOCTYPE frameset SYSTEM "frameset.dtd">
<frameset>
<predicate lemma="decide">
<note>
  Frames file for 'decide' based on survey of initial sentences of big
  corpus. 
</note>

<roleset id="decide.01" name="decide">
<roles>
  <role descr="decider" n="0"/>
  <role descr="decision" n="1"/>
  <role descr="benefactive" n="2"/>
  <role descr="instrument" n="3"/>
</roles>

<example name="decide a predicate">
  <text>
  The city decided *trace* to treat its guests more like royalty or
  rock stars than factory owners.
  </text>
  <arg n="0">The city</arg>
  <rel>decided</rel>
  <arg n="1">*trace* to treat its guests more like royalty or
  rock stars than factory owners</arg>
</example>

<example name="decide a preposition: benefactive">
  <text>
  The court decided for John.
  </text>
  <arg n="0">The court</arg>
  <rel>decided</rel>
  <arg f="for" n="2">for John</arg>
</example>

<example name="decide a preposition: decision">
  <text>
  After perusing the extensive wine list for an hour, John decided on
  the Mad Dog.
  </text>
  <arg f="TMP" n="m">After perusing the extensive wine list for an hour</arg>
  <arg n="0">John</arg>
  <rel>decided</rel>
  <arg f="on" n="1">the Mad Dog</arg>
</example>

<example name="decide a sentence">
  <text>
  A good number decide (that) it's not worth it.
  </text>
  <arg n="0">A good number</arg>
  <rel>decide</rel>
  <arg n="1">it's not worth it</arg>
</example>

<example name="instrumental subject">
  <text>
  John's home run decided the game.
  </text>
  <arg n="3">John's home run</arg>
  <rel>decided</rel>
  <arg n="1">the game</arg>
</example>

<example name="instrumental object?">
  <text>
  The game was decided with/by John's home run.
  </text>
  <arg n="1">The game</arg>
  <rel>decided</rel>
  <arg f="with/by" n="3">John's home run</arg>
</example>

<note>
Maybe these last two should be regarded as a separate sense/roleset;
they essentially mean &quot;cause an unstated entity to make a decision&quot;.
They're also different in that they take a straight nominal &quot;decision&quot;.
</note>

</roleset>
</predicate>
</frameset>
