<!DOCTYPE frameset SYSTEM "frameset.dtd">
<frameset>
<predicate lemma="intimidate">
<note>
  Frames file for 'intimidate' based on survey of sentences in the WSJ
  corpus. 
</note>

<roleset id="intimidate.01" name="to make timid, fill with fear" vncls="-">
<roles>
  <role descr="intimidating entity" n="0"/>
  <role descr="entity intimidated" n="1"/>
</roles>

<example name="transitive">
<inflection aspect="ns" form="full" person="ns" tense="present" voice="active"/>
<text>
 Congress learned during the Reagan administration that it could intimidate the executive branch by [*-1] uttering again and again the same seven words : `` Provided , that no funds shall be spent [*-48] ... . ''
</text>
	<arg n="0">it</arg>
	<arg f="MOD" n="M">could</arg>
	<rel>intimidate</rel>
	<arg n="1">the executive branch</arg>
	<arg f="MNR" n="M">by [*-1] uttering again and again the same seven words : `` Provided , that no funds shall be spent [*-48]</arg>
</example>





</roleset>
</predicate>


</frameset>
